netorcai/client.py
netorcai/message.py
netorcai/version.py
netorcai-2.0.0.dist-info/LICENSE
netorcai-2.0.0.dist-info/METADATA
netorcai-2.0.0.dist-info/WHEEL
netorcai-2.0.0.dist-info/top_level.txt
netorcai-2.0.0.dist-info/RECORD
